game/__init__.py
game/casts.py
game/config.py
game/constants.py
game/frames.py
game/muser.py
game/sounds.py
game/ui.py
game/widgets.py
game/playthrough/__init__.py
game/playthrough/base_note.py
game/playthrough/fancy_note.py
game/playthrough/frame_note.py
game/playthrough/manager_actions.py
game/playthrough/note.py
game/playthrough/note_manager.py
sheet/__init__.py
sheet/actions.py
sheet/note.py
sheet/sheet_constants.py
sheet/gen/__init__.py
sheet/gen/abs_output.py
sheet/gen/effector.py
sheet/gen/generator.py
sheet/gen/meta_input.py
sheet/gen/midi_converter.py
sheet/gen/rel_input.py
sheet/gen/sheet_output.py
sheet/reader/__init__.py
sheet/reader/sheet_reader.py
muser-1.2.1.2.dist-info/METADATA
muser-1.2.1.2.dist-info/WHEEL
muser-1.2.1.2.dist-info/entry_points.txt
muser-1.2.1.2.dist-info/top_level.txt
muser-1.2.1.2.dist-info/RECORD
