Metadata-Version: 2.1
Name: muser
Version: 1.2.1.2
Summary: A musical game made using pyxel
Home-page: https://github.com/Qiufeng54321/muser
Author: Qiufeng54321
Author-email: williamcraft@163.com
License: GPLv3
Keywords: pyxel
Platform: UNKNOWN
Classifier: Programming Language :: Python :: 3
Classifier: License :: OSI Approved :: GNU General Public License v3 (GPLv3)
Classifier: Operating System :: OS Independent
Requires-Dist: pygame (>=1.9.6)
Requires-Dist: pyglet (>=1.4.7)
Requires-Dist: PyInstaller (>=3.5)
Requires-Dist: pyxel (>=1.2.10)
Requires-Dist: mido (>=1.2.9)
